galax/__init__.py
galax/__init__.pyi
galax/_version.py
galax/_version.pyi
galax/py.typed
galax/setup_package.py
galax/typing.py
galax/coordinates/__init__.py
galax/coordinates/__init__.pyi
galax/coordinates/_compat.py
galax/coordinates/_psp/__init__.py
galax/coordinates/_psp/base.py
galax/coordinates/_psp/base_composite.py
galax/coordinates/_psp/base_psp.py
galax/coordinates/_psp/compat_apy.py
galax/coordinates/_psp/core.py
galax/coordinates/_psp/interp.py
galax/coordinates/_psp/operator_compat.py
galax/coordinates/_psp/utils.py
galax/coordinates/operators/__init__.py
galax/coordinates/operators/_rotating.py
galax/dynamics/__init__.py
galax/dynamics/__init__.pyi
galax/dynamics/_compat.py
galax/dynamics/_dynamics/__init__.py
galax/dynamics/_dynamics/base.py
galax/dynamics/_dynamics/orbit.py
galax/dynamics/_dynamics/integrate/__init__.py
galax/dynamics/_dynamics/integrate/_api.py
galax/dynamics/_dynamics/integrate/_base.py
galax/dynamics/_dynamics/integrate/_builtin.py
galax/dynamics/_dynamics/integrate/_funcs.py
galax/dynamics/_dynamics/mockstream/__init__.py
galax/dynamics/_dynamics/mockstream/_moving.py
galax/dynamics/_dynamics/mockstream/core.py
galax/dynamics/_dynamics/mockstream/mockstream_generator.py
galax/dynamics/_dynamics/mockstream/utils.py
galax/dynamics/_dynamics/mockstream/df/__init__.py
galax/dynamics/_dynamics/mockstream/df/_base.py
galax/dynamics/_dynamics/mockstream/df/_fardal.py
galax/dynamics/_dynamics/mockstream/df/_progenitor.py
galax/potential/__init__.py
galax/potential/__init__.pyi
galax/potential/_potential/__init__.py
galax/potential/_potential/base.py
galax/potential/_potential/composite.py
galax/potential/_potential/core.py
galax/potential/_potential/frame.py
galax/potential/_potential/funcs.py
galax/potential/_potential/utils.py
galax/potential/_potential/builtin/__init__.py
galax/potential/_potential/builtin/bars.py
galax/potential/_potential/builtin/builtin.py
galax/potential/_potential/builtin/logarithmic.py
galax-0.0.2.dist-info/METADATA
galax-0.0.2.dist-info/WHEEL
galax-0.0.2.dist-info/licenses/AUTHORS.rst
galax-0.0.2.dist-info/licenses/LICENSE
galax-0.0.2.dist-info/RECORD
